posim/__init__.py
posim/convert.py
posim/noise.py
posim/paths.py
posim/simulate.py
posim/utils.py
posim/velocities.py
posim-0.1.dist-info/LICENSE
posim-0.1.dist-info/METADATA
posim-0.1.dist-info/WHEEL
posim-0.1.dist-info/top_level.txt
posim-0.1.dist-info/RECORD
