Metadata-Version: 2.1
Name: posim
Version: 0.1
Summary: A library for generating simulated positioning data for testing GNSS applications.
Home-page: https://github.com/zrowland885/posim
Author: zrowland885
Author-email: zrowland885@gmail.com
License: UNKNOWN
Project-URL: Bug Tracker, https://github.com/zrowland885/posim/issues
Platform: UNKNOWN
Classifier: Programming Language :: Python :: 3
Classifier: License :: OSI Approved :: MIT License
Classifier: Operating System :: OS Independent
Requires-Python: >=3.6
License-File: LICENSE
Requires-Dist: numpy
Requires-Dist: geographiclib
Requires-Dist: matplotlib
